flask_dba/__init__.py
flask_dba/exceptions/__init__.py
flask_dba/exceptions/utils.py
flask_dba/models/utils.py
flask_dba/models/agendamento/__init__.py
flask_dba/models/agendamento/agendamento.py
flask_dba/models/agendamento/coleta.py
flask_dba/models/agendamento/credencial.py
flask_dba/models/agendamento/execucao.py
flask_dba/models/agendamento/execucao_item.py
flask_dba/models/base/__init__.py
flask_dba/models/base/endereco.py
flask_dba/models/empresa/__init__.py
flask_dba/models/empresa/colaborador.py
flask_dba/models/empresa/empresa.py
flask_dba/models/endereco/__init__.py
flask_dba/models/permission/__init__.py
flask_dba/models/permission/grupo.py
flask_dba/models/permission/grupo_usuario.py
flask_dba/models/permission/permissao.py
flask_dba/models/permission/permissao_grupo.py
flask_dba/models/permission/permissao_usuario.py
flask_dba/models/usuario/__init__.py
flask_dba-1.1.0.dist-info/METADATA
flask_dba-1.1.0.dist-info/WHEEL
flask_dba-1.1.0.dist-info/top_level.txt
flask_dba-1.1.0.dist-info/RECORD
