Metadata-Version: 2.1
Name: flask-dba
Version: 1.1.0
Summary: Extenção flask para aumento de agilidade no processo de criação de projeto.
Home-page: https://github.com/feiticeiro-tec/flask_dba
Author: Silvio Henrique Cruz Da Silva
Author-email: silviohenriquecruzdasilva@gmail.com
License: BSD3
Keywords: Pacote
Requires-Dist: flask
Requires-Dist: flask-sqlalchemy
Requires-Dist: loguru
